{
  "generated_at": "2025-11-17T06:39:07Z",
  "source_file": "data/UGA/UGA_combined_areas.topojson",
  "total_unsimplified": 83,
  "items": [
    {
      "title": "Abim",
      "id": "18724695",
      "country": "UGA",
      "year": 2020,
      "reason": "no_change",
      "detail": "Simplified geometry matches original",
      "source_dataset": "data/UGA/UGA_combined_areas.topojson",
      "from": "Jun 2020",
      "to": "Aug 2020"
    },
    {
      "title": "Kaabong",
      "id": "18724697",
      "country": "UGA",
      "year": 2020,
      "reason": "no_change",
      "detail": "Simplified geometry matches original",
      "source_dataset": "data/UGA/UGA_combined_areas.topojson",
      "from": "Jun 2020",
      "to": "Aug 2020"
    },
    {
      "title": "Arua (Madi Okollo & Terego)",
      "id": "18724711",
      "country": "UGA",
      "year": 2020,
      "reason": "no_change",
      "detail": "Simplified geometry matches original",
      "source_dataset": "data/UGA/UGA_combined_areas.topojson",
      "from": "Jun 2020",
      "to": "Aug 2020"
    },
    {
      "title": "Central division",
      "id": "18724716",
      "country": "UGA",
      "year": 2020,
      "reason": "no_change",
      "detail": "Simplified geometry matches original",
      "source_dataset": "data/UGA/UGA_combined_areas.topojson",
      "from": "Jun 2020",
      "to": "Aug 2020"
    },
    {
      "title": "Lubaga division",
      "id": "18724724",
      "country": "UGA",
      "year": 2020,
      "reason": "no_change",
      "detail": "Simplified geometry matches original",
      "source_dataset": "data/UGA/UGA_combined_areas.topojson",
      "from": "Jun 2020",
      "to": "Aug 2020"
    },
    {
      "title": "Makindye division",
      "id": "18724732",
      "country": "UGA",
      "year": 2020,
      "reason": "no_change",
      "detail": "Simplified geometry matches original",
      "source_dataset": "data/UGA/UGA_combined_areas.topojson",
      "from": "Jun 2020",
      "to": "Aug 2020"
    },
    {
      "title": "Isingiro",
      "id": "18724734",
      "country": "UGA",
      "year": 2020,
      "reason": "no_change",
      "detail": "Simplified geometry matches original",
      "source_dataset": "data/UGA/UGA_combined_areas.topojson",
      "from": "Jun 2020",
      "to": "Aug 2020"
    },
    {
      "title": "Kamwenge",
      "id": "18724742",
      "country": "UGA",
      "year": 2020,
      "reason": "no_change",
      "detail": "Simplified geometry matches original",
      "source_dataset": "data/UGA/UGA_combined_areas.topojson",
      "from": "Jun 2020",
      "to": "Aug 2020"
    },
    {
      "title": "Kawempe division",
      "id": "18724746",
      "country": "UGA",
      "year": 2020,
      "reason": "no_change",
      "detail": "Simplified geometry matches original",
      "source_dataset": "data/UGA/UGA_combined_areas.topojson",
      "from": "Jun 2020",
      "to": "Aug 2020"
    },
    {
      "title": "Kikuube (from Hoima)",
      "id": "18724748",
      "country": "UGA",
      "year": 2020,
      "reason": "no_change",
      "detail": "Simplified geometry matches original",
      "source_dataset": "data/UGA/UGA_combined_areas.topojson",
      "from": "Jun 2020",
      "to": "Aug 2020"
    },
    {
      "title": "Kiryandongo District",
      "id": "18724750",
      "country": "UGA",
      "year": 2020,
      "reason": "no_change",
      "detail": "Simplified geometry matches original",
      "source_dataset": "data/UGA/UGA_combined_areas.topojson",
      "from": "Jun 2020",
      "to": "Aug 2020"
    },
    {
      "title": "Koboko",
      "id": "18724754",
      "country": "UGA",
      "year": 2020,
      "reason": "no_change",
      "detail": "Simplified geometry matches original",
      "source_dataset": "data/UGA/UGA_combined_areas.topojson",
      "from": "Jun 2020",
      "to": "Aug 2020"
    },
    {
      "title": "Kyegegwa",
      "id": "18724760",
      "country": "UGA",
      "year": 2020,
      "reason": "no_change",
      "detail": "Simplified geometry matches original",
      "source_dataset": "data/UGA/UGA_combined_areas.topojson",
      "from": "Jun 2020",
      "to": "Aug 2020"
    },
    {
      "title": "Lamwo",
      "id": "18724764",
      "country": "UGA",
      "year": 2020,
      "reason": "no_change",
      "detail": "Simplified geometry matches original",
      "source_dataset": "data/UGA/UGA_combined_areas.topojson",
      "from": "Jun 2020",
      "to": "Aug 2020"
    },
    {
      "title": "Nakawa division",
      "id": "18724772",
      "country": "UGA",
      "year": 2020,
      "reason": "no_change",
      "detail": "Simplified geometry matches original",
      "source_dataset": "data/UGA/UGA_combined_areas.topojson",
      "from": "Jun 2020",
      "to": "Aug 2020"
    },
    {
      "title": "Yumbe",
      "id": "18724780",
      "country": "UGA",
      "year": 2020,
      "reason": "no_change",
      "detail": "Simplified geometry matches original",
      "source_dataset": "data/UGA/UGA_combined_areas.topojson",
      "from": "Jun 2020",
      "to": "Aug 2020"
    },
    {
      "title": "Amudat",
      "id": "18724782",
      "country": "UGA",
      "year": 2020,
      "reason": "no_change",
      "detail": "Simplified geometry matches original",
      "source_dataset": "data/UGA/UGA_combined_areas.topojson",
      "from": "Jun 2020",
      "to": "Aug 2020"
    },
    {
      "title": "Karenga",
      "id": "18724784",
      "country": "UGA",
      "year": 2020,
      "reason": "no_change",
      "detail": "Simplified geometry matches original",
      "source_dataset": "data/UGA/UGA_combined_areas.topojson",
      "from": "Jun 2020",
      "to": "Aug 2020"
    },
    {
      "title": "Kotido",
      "id": "18724786",
      "country": "UGA",
      "year": 2020,
      "reason": "no_change",
      "detail": "Simplified geometry matches original",
      "source_dataset": "data/UGA/UGA_combined_areas.topojson",
      "from": "Jun 2020",
      "to": "Aug 2020"
    },
    {
      "title": "Moroto",
      "id": "18724788",
      "country": "UGA",
      "year": 2020,
      "reason": "no_change",
      "detail": "Simplified geometry matches original",
      "source_dataset": "data/UGA/UGA_combined_areas.topojson",
      "from": "Jun 2020",
      "to": "Aug 2020"
    },
    {
      "title": "Napak",
      "id": "18724790",
      "country": "UGA",
      "year": 2020,
      "reason": "no_change",
      "detail": "Simplified geometry matches original",
      "source_dataset": "data/UGA/UGA_combined_areas.topojson",
      "from": "Jun 2020",
      "to": "Aug 2020"
    },
    {
      "title": "Nabilatuk",
      "id": "18724792",
      "country": "UGA",
      "year": 2020,
      "reason": "no_change",
      "detail": "Simplified geometry matches original",
      "source_dataset": "data/UGA/UGA_combined_areas.topojson",
      "from": "Jun 2020",
      "to": "Aug 2020"
    },
    {
      "title": "Nakapiripirit",
      "id": "18724794",
      "country": "UGA",
      "year": 2020,
      "reason": "no_change",
      "detail": "Simplified geometry matches original",
      "source_dataset": "data/UGA/UGA_combined_areas.topojson",
      "from": "Jun 2020",
      "to": "Aug 2020"
    },
    {
      "title": "Nabilatuk",
      "id": "23934895",
      "country": "UGA",
      "year": 2021,
      "reason": "no_change",
      "detail": "Simplified geometry matches original",
      "source_dataset": "data/UGA/UGA_combined_areas.topojson",
      "from": "Mar 2021",
      "to": "Jul 2021"
    },
    {
      "title": "Nakapiripirit",
      "id": "23934897",
      "country": "UGA",
      "year": 2021,
      "reason": "no_change",
      "detail": "Simplified geometry matches original",
      "source_dataset": "data/UGA/UGA_combined_areas.topojson",
      "from": "Mar 2021",
      "to": "Jul 2021"
    },
    {
      "title": "Abim",
      "id": "23934899",
      "country": "UGA",
      "year": 2021,
      "reason": "no_change",
      "detail": "Simplified geometry matches original",
      "source_dataset": "data/UGA/UGA_combined_areas.topojson",
      "from": "Mar 2021",
      "to": "Jul 2021"
    },
    {
      "title": "Kotido",
      "id": "23934901",
      "country": "UGA",
      "year": 2021,
      "reason": "no_change",
      "detail": "Simplified geometry matches original",
      "source_dataset": "data/UGA/UGA_combined_areas.topojson",
      "from": "Mar 2021",
      "to": "Jul 2021"
    },
    {
      "title": "Amudat",
      "id": "23934903",
      "country": "UGA",
      "year": 2021,
      "reason": "no_change",
      "detail": "Simplified geometry matches original",
      "source_dataset": "data/UGA/UGA_combined_areas.topojson",
      "from": "Mar 2021",
      "to": "Jul 2021"
    },
    {
      "title": "Moroto",
      "id": "23934905",
      "country": "UGA",
      "year": 2021,
      "reason": "no_change",
      "detail": "Simplified geometry matches original",
      "source_dataset": "data/UGA/UGA_combined_areas.topojson",
      "from": "Mar 2021",
      "to": "Jul 2021"
    },
    {
      "title": "Napak",
      "id": "23934907",
      "country": "UGA",
      "year": 2021,
      "reason": "no_change",
      "detail": "Simplified geometry matches original",
      "source_dataset": "data/UGA/UGA_combined_areas.topojson",
      "from": "Mar 2021",
      "to": "Jul 2021"
    },
    {
      "title": "Kaabong",
      "id": "23934909",
      "country": "UGA",
      "year": 2021,
      "reason": "no_change",
      "detail": "Simplified geometry matches original",
      "source_dataset": "data/UGA/UGA_combined_areas.topojson",
      "from": "Mar 2021",
      "to": "Jul 2021"
    },
    {
      "title": "Karenga",
      "id": "23934911",
      "country": "UGA",
      "year": 2021,
      "reason": "no_change",
      "detail": "Simplified geometry matches original",
      "source_dataset": "data/UGA/UGA_combined_areas.topojson",
      "from": "Mar 2021",
      "to": "Jul 2021"
    },
    {
      "title": "Moroto",
      "id": "26669921",
      "country": "UGA",
      "year": 2022,
      "reason": "no_change",
      "detail": "Simplified geometry matches original",
      "source_dataset": "data/UGA/UGA_combined_areas.topojson",
      "from": "Jun 2022",
      "to": "Aug 2022"
    },
    {
      "title": "Abim",
      "id": "26669923",
      "country": "UGA",
      "year": 2022,
      "reason": "no_change",
      "detail": "Simplified geometry matches original",
      "source_dataset": "data/UGA/UGA_combined_areas.topojson",
      "from": "Jun 2022",
      "to": "Aug 2022"
    },
    {
      "title": "Karenga",
      "id": "26669925",
      "country": "UGA",
      "year": 2022,
      "reason": "no_change",
      "detail": "Simplified geometry matches original",
      "source_dataset": "data/UGA/UGA_combined_areas.topojson",
      "from": "Jun 2022",
      "to": "Aug 2022"
    },
    {
      "title": "Nakapiripirit",
      "id": "26669927",
      "country": "UGA",
      "year": 2022,
      "reason": "no_change",
      "detail": "Simplified geometry matches original",
      "source_dataset": "data/UGA/UGA_combined_areas.topojson",
      "from": "Jun 2022",
      "to": "Aug 2022"
    },
    {
      "title": "Amudat",
      "id": "26669929",
      "country": "UGA",
      "year": 2022,
      "reason": "no_change",
      "detail": "Simplified geometry matches original",
      "source_dataset": "data/UGA/UGA_combined_areas.topojson",
      "from": "Jun 2022",
      "to": "Aug 2022"
    },
    {
      "title": "Napak",
      "id": "26669931",
      "country": "UGA",
      "year": 2022,
      "reason": "no_change",
      "detail": "Simplified geometry matches original",
      "source_dataset": "data/UGA/UGA_combined_areas.topojson",
      "from": "Jun 2022",
      "to": "Aug 2022"
    },
    {
      "title": "Nabilatuk",
      "id": "26669933",
      "country": "UGA",
      "year": 2022,
      "reason": "no_change",
      "detail": "Simplified geometry matches original",
      "source_dataset": "data/UGA/UGA_combined_areas.topojson",
      "from": "Jun 2022",
      "to": "Aug 2022"
    },
    {
      "title": "Kotido",
      "id": "26669935",
      "country": "UGA",
      "year": 2022,
      "reason": "no_change",
      "detail": "Simplified geometry matches original",
      "source_dataset": "data/UGA/UGA_combined_areas.topojson",
      "from": "Jun 2022",
      "to": "Aug 2022"
    },
    {
      "title": "Kaabong",
      "id": "26669937",
      "country": "UGA",
      "year": 2022,
      "reason": "no_change",
      "detail": "Simplified geometry matches original",
      "source_dataset": "data/UGA/UGA_combined_areas.topojson",
      "from": "Jun 2022",
      "to": "Aug 2022"
    },
    {
      "title": "Amuria",
      "id": "26670024",
      "country": "UGA",
      "year": 2022,
      "reason": "no_change",
      "detail": "Simplified geometry matches original",
      "source_dataset": "data/UGA/UGA_combined_areas.topojson",
      "from": "Jun 2022",
      "to": "Aug 2022"
    },
    {
      "title": "Terego",
      "id": "26670033",
      "country": "UGA",
      "year": 2022,
      "reason": "no_change",
      "detail": "Simplified geometry matches original",
      "source_dataset": "data/UGA/UGA_combined_areas.topojson",
      "from": "Jun 2022",
      "to": "Aug 2022"
    },
    {
      "title": "Bukedea",
      "id": "26670054",
      "country": "UGA",
      "year": 2022,
      "reason": "no_change",
      "detail": "Simplified geometry matches original",
      "source_dataset": "data/UGA/UGA_combined_areas.topojson",
      "from": "Jun 2022",
      "to": "Aug 2022"
    },
    {
      "title": "Isingiro",
      "id": "26670114",
      "country": "UGA",
      "year": 2022,
      "reason": "no_change",
      "detail": "Simplified geometry matches original",
      "source_dataset": "data/UGA/UGA_combined_areas.topojson",
      "from": "Jun 2022",
      "to": "Aug 2022"
    },
    {
      "title": "Kaberamaido",
      "id": "26670129",
      "country": "UGA",
      "year": 2022,
      "reason": "no_change",
      "detail": "Simplified geometry matches original",
      "source_dataset": "data/UGA/UGA_combined_areas.topojson",
      "from": "Jun 2022",
      "to": "Aug 2022"
    },
    {
      "title": "Kamwenge",
      "id": "26670156",
      "country": "UGA",
      "year": 2022,
      "reason": "no_change",
      "detail": "Simplified geometry matches original",
      "source_dataset": "data/UGA/UGA_combined_areas.topojson",
      "from": "Jun 2022",
      "to": "Aug 2022"
    },
    {
      "title": "Kapelebyong",
      "id": "26670165",
      "country": "UGA",
      "year": 2022,
      "reason": "no_change",
      "detail": "Simplified geometry matches original",
      "source_dataset": "data/UGA/UGA_combined_areas.topojson",
      "from": "Jun 2022",
      "to": "Aug 2022"
    },
    {
      "title": "Katakwi",
      "id": "26670177",
      "country": "UGA",
      "year": 2022,
      "reason": "no_change",
      "detail": "Simplified geometry matches original",
      "source_dataset": "data/UGA/UGA_combined_areas.topojson",
      "from": "Jun 2022",
      "to": "Aug 2022"
    },
    {
      "title": "Kikuube",
      "id": "26670195",
      "country": "UGA",
      "year": 2022,
      "reason": "no_change",
      "detail": "Simplified geometry matches original",
      "source_dataset": "data/UGA/UGA_combined_areas.topojson",
      "from": "Jun 2022",
      "to": "Aug 2022"
    },
    {
      "title": "Kiryandongo",
      "id": "26670201",
      "country": "UGA",
      "year": 2022,
      "reason": "no_change",
      "detail": "Simplified geometry matches original",
      "source_dataset": "data/UGA/UGA_combined_areas.topojson",
      "from": "Jun 2022",
      "to": "Aug 2022"
    },
    {
      "title": "Koboko",
      "id": "26670213",
      "country": "UGA",
      "year": 2022,
      "reason": "no_change",
      "detail": "Simplified geometry matches original",
      "source_dataset": "data/UGA/UGA_combined_areas.topojson",
      "from": "Jun 2022",
      "to": "Aug 2022"
    },
    {
      "title": "Kumi",
      "id": "26670222",
      "country": "UGA",
      "year": 2022,
      "reason": "no_change",
      "detail": "Simplified geometry matches original",
      "source_dataset": "data/UGA/UGA_combined_areas.topojson",
      "from": "Jun 2022",
      "to": "Aug 2022"
    },
    {
      "title": "Kyegegwa",
      "id": "26670234",
      "country": "UGA",
      "year": 2022,
      "reason": "no_change",
      "detail": "Simplified geometry matches original",
      "source_dataset": "data/UGA/UGA_combined_areas.topojson",
      "from": "Jun 2022",
      "to": "Aug 2022"
    },
    {
      "title": "Lamwo",
      "id": "26670243",
      "country": "UGA",
      "year": 2022,
      "reason": "no_change",
      "detail": "Simplified geometry matches original",
      "source_dataset": "data/UGA/UGA_combined_areas.topojson",
      "from": "Jun 2022",
      "to": "Aug 2022"
    },
    {
      "title": "Madi okollo",
      "id": "26670261",
      "country": "UGA",
      "year": 2022,
      "reason": "no_change",
      "detail": "Simplified geometry matches original",
      "source_dataset": "data/UGA/UGA_combined_areas.topojson",
      "from": "Jun 2022",
      "to": "Aug 2022"
    },
    {
      "title": "Ngora",
      "id": "26670333",
      "country": "UGA",
      "year": 2022,
      "reason": "no_change",
      "detail": "Simplified geometry matches original",
      "source_dataset": "data/UGA/UGA_combined_areas.topojson",
      "from": "Jun 2022",
      "to": "Aug 2022"
    },
    {
      "title": "Obongi",
      "id": "26670345",
      "country": "UGA",
      "year": 2022,
      "reason": "no_change",
      "detail": "Simplified geometry matches original",
      "source_dataset": "data/UGA/UGA_combined_areas.topojson",
      "from": "Jun 2022",
      "to": "Aug 2022"
    },
    {
      "title": "Serere",
      "id": "26670384",
      "country": "UGA",
      "year": 2022,
      "reason": "no_change",
      "detail": "Simplified geometry matches original",
      "source_dataset": "data/UGA/UGA_combined_areas.topojson",
      "from": "Jun 2022",
      "to": "Aug 2022"
    },
    {
      "title": "Soroti",
      "id": "26670393",
      "country": "UGA",
      "year": 2022,
      "reason": "no_change",
      "detail": "Simplified geometry matches original",
      "source_dataset": "data/UGA/UGA_combined_areas.topojson",
      "from": "Jun 2022",
      "to": "Aug 2022"
    },
    {
      "title": "Yumbe",
      "id": "26670405",
      "country": "UGA",
      "year": 2022,
      "reason": "no_change",
      "detail": "Simplified geometry matches original",
      "source_dataset": "data/UGA/UGA_combined_areas.topojson",
      "from": "Jun 2022",
      "to": "Aug 2022"
    },
    {
      "title": "Lamwo",
      "id": "62468628",
      "country": "UGA",
      "year": 2023,
      "reason": "no_change",
      "detail": "Simplified geometry matches original",
      "source_dataset": "data/UGA/UGA_combined_areas.topojson",
      "from": "Aug 2023",
      "to": "Jan 2024"
    },
    {
      "title": "Kyegegwa",
      "id": "62468630",
      "country": "UGA",
      "year": 2023,
      "reason": "no_change",
      "detail": "Simplified geometry matches original",
      "source_dataset": "data/UGA/UGA_combined_areas.topojson",
      "from": "Aug 2023",
      "to": "Jan 2024"
    },
    {
      "title": "Yumbe",
      "id": "62468632",
      "country": "UGA",
      "year": 2023,
      "reason": "no_change",
      "detail": "Simplified geometry matches original",
      "source_dataset": "data/UGA/UGA_combined_areas.topojson",
      "from": "Aug 2023",
      "to": "Jan 2024"
    },
    {
      "title": "Koboko",
      "id": "62468634",
      "country": "UGA",
      "year": 2023,
      "reason": "no_change",
      "detail": "Simplified geometry matches original",
      "source_dataset": "data/UGA/UGA_combined_areas.topojson",
      "from": "Aug 2023",
      "to": "Jan 2024"
    },
    {
      "title": "Kamwenge",
      "id": "62468636",
      "country": "UGA",
      "year": 2023,
      "reason": "no_change",
      "detail": "Simplified geometry matches original",
      "source_dataset": "data/UGA/UGA_combined_areas.topojson",
      "from": "Aug 2023",
      "to": "Jan 2024"
    },
    {
      "title": "Kikuube",
      "id": "62468638",
      "country": "UGA",
      "year": 2023,
      "reason": "no_change",
      "detail": "Simplified geometry matches original",
      "source_dataset": "data/UGA/UGA_combined_areas.topojson",
      "from": "Aug 2023",
      "to": "Jan 2024"
    },
    {
      "title": "Obongi",
      "id": "62468640",
      "country": "UGA",
      "year": 2023,
      "reason": "no_change",
      "detail": "Simplified geometry matches original",
      "source_dataset": "data/UGA/UGA_combined_areas.topojson",
      "from": "Aug 2023",
      "to": "Jan 2024"
    },
    {
      "title": "Terego",
      "id": "62468642",
      "country": "UGA",
      "year": 2023,
      "reason": "no_change",
      "detail": "Simplified geometry matches original",
      "source_dataset": "data/UGA/UGA_combined_areas.topojson",
      "from": "Aug 2023",
      "to": "Jan 2024"
    },
    {
      "title": "Madi okollo",
      "id": "62468644",
      "country": "UGA",
      "year": 2023,
      "reason": "no_change",
      "detail": "Simplified geometry matches original",
      "source_dataset": "data/UGA/UGA_combined_areas.topojson",
      "from": "Aug 2023",
      "to": "Jan 2024"
    },
    {
      "title": "Isingiro",
      "id": "62468648",
      "country": "UGA",
      "year": 2023,
      "reason": "no_change",
      "detail": "Simplified geometry matches original",
      "source_dataset": "data/UGA/UGA_combined_areas.topojson",
      "from": "Aug 2023",
      "to": "Jan 2024"
    },
    {
      "title": "Kiryandongo",
      "id": "62468650",
      "country": "UGA",
      "year": 2023,
      "reason": "no_change",
      "detail": "Simplified geometry matches original",
      "source_dataset": "data/UGA/UGA_combined_areas.topojson",
      "from": "Aug 2023",
      "to": "Jan 2024"
    },
    {
      "title": "Lamwo",
      "id": "73897525",
      "country": "UGA",
      "year": 2024,
      "reason": "no_change",
      "detail": "Simplified geometry matches original",
      "source_dataset": "data/UGA/UGA_combined_areas.topojson",
      "from": "Jul 2024",
      "to": "Jan 2025"
    },
    {
      "title": "Kyegegwa",
      "id": "73897527",
      "country": "UGA",
      "year": 2024,
      "reason": "no_change",
      "detail": "Simplified geometry matches original",
      "source_dataset": "data/UGA/UGA_combined_areas.topojson",
      "from": "Jul 2024",
      "to": "Jan 2025"
    },
    {
      "title": "Yumbe",
      "id": "73897529",
      "country": "UGA",
      "year": 2024,
      "reason": "no_change",
      "detail": "Simplified geometry matches original",
      "source_dataset": "data/UGA/UGA_combined_areas.topojson",
      "from": "Jul 2024",
      "to": "Jan 2025"
    },
    {
      "title": "Koboko",
      "id": "73897531",
      "country": "UGA",
      "year": 2024,
      "reason": "no_change",
      "detail": "Simplified geometry matches original",
      "source_dataset": "data/UGA/UGA_combined_areas.topojson",
      "from": "Jul 2024",
      "to": "Jan 2025"
    },
    {
      "title": "Kamwenge",
      "id": "73897533",
      "country": "UGA",
      "year": 2024,
      "reason": "no_change",
      "detail": "Simplified geometry matches original",
      "source_dataset": "data/UGA/UGA_combined_areas.topojson",
      "from": "Jul 2024",
      "to": "Jan 2025"
    },
    {
      "title": "Kikuube",
      "id": "73897535",
      "country": "UGA",
      "year": 2024,
      "reason": "no_change",
      "detail": "Simplified geometry matches original",
      "source_dataset": "data/UGA/UGA_combined_areas.topojson",
      "from": "Jul 2024",
      "to": "Jan 2025"
    },
    {
      "title": "Obongi",
      "id": "73897537",
      "country": "UGA",
      "year": 2024,
      "reason": "no_change",
      "detail": "Simplified geometry matches original",
      "source_dataset": "data/UGA/UGA_combined_areas.topojson",
      "from": "Jul 2024",
      "to": "Jan 2025"
    },
    {
      "title": "Terego",
      "id": "73897539",
      "country": "UGA",
      "year": 2024,
      "reason": "no_change",
      "detail": "Simplified geometry matches original",
      "source_dataset": "data/UGA/UGA_combined_areas.topojson",
      "from": "Jul 2024",
      "to": "Jan 2025"
    },
    {
      "title": "Madi okollo",
      "id": "73897541",
      "country": "UGA",
      "year": 2024,
      "reason": "no_change",
      "detail": "Simplified geometry matches original",
      "source_dataset": "data/UGA/UGA_combined_areas.topojson",
      "from": "Jul 2024",
      "to": "Jan 2025"
    },
    {
      "title": "Isingiro",
      "id": "73897543",
      "country": "UGA",
      "year": 2024,
      "reason": "no_change",
      "detail": "Simplified geometry matches original",
      "source_dataset": "data/UGA/UGA_combined_areas.topojson",
      "from": "Jul 2024",
      "to": "Jan 2025"
    },
    {
      "title": "Kiryandongo",
      "id": "73897545",
      "country": "UGA",
      "year": 2024,
      "reason": "no_change",
      "detail": "Simplified geometry matches original",
      "source_dataset": "data/UGA/UGA_combined_areas.topojson",
      "from": "Jul 2024",
      "to": "Jan 2025"
    }
  ]
}